breaks_machine/__init__.py
breaks_machine/cli.py
breaks_machine/converter.py
breaks_machine/detector.py
breaks_machine/processor.py
breaks_machine/stretcher.py
breaks_machine-0.2.0.dist-info/METADATA
breaks_machine-0.2.0.dist-info/WHEEL
breaks_machine-0.2.0.dist-info/entry_points.txt
breaks_machine-0.2.0.dist-info/licenses/LICENSE
breaks_machine-0.2.0.dist-info/RECORD
