Metadata-Version: 2.4
Name: breaks-machine
Version: 0.2.0
Summary: Time-stretch drum breaks to target BPMs with automatic tempo detection
Author-email: Thomas John Flaherty <thomas@example.com>
License: MIT
License-File: LICENSE
Keywords: audio,bpm,breaks,drums,music,tempo,time-stretch
Classifier: Development Status :: 4 - Beta
Classifier: Intended Audience :: Developers
Classifier: Intended Audience :: End Users/Desktop
Classifier: License :: OSI Approved :: MIT License
Classifier: Programming Language :: Python :: 3
Classifier: Programming Language :: Python :: 3.13
Classifier: Topic :: Multimedia :: Sound/Audio
Classifier: Topic :: Multimedia :: Sound/Audio :: Analysis
Requires-Python: >=3.13
Requires-Dist: click>=8.3.1
Requires-Dist: librosa>=0.11.0
Requires-Dist: pyrubberband>=0.4.0
Requires-Dist: soundfile>=0.13.1
